{
    "generated_at": "2026-07-13T18:23:55.781588+00:00",
    "currency": "EUR",
    "summary": {
        "banks_processed": 3,
        "lowest_buy": {
            "bank": "EBL",
            "value": 138.04
        },
        "highest_buy": {
            "bank": "BRAC",
            "value": 139.3874
        },
        "lowest_sell": {
            "bank": "BRAC",
            "value": 142.0954
        },
        "highest_sell": {
            "bank": "EBL",
            "value": 142.91
        },
        "average_buy": 138.85483333333335,
        "average_sell": 142.39806666666667
    },
    "banks": [
        {
            "bank": "EBL",
            "currency": "EUR",
            "buy": 138.04,
            "sell": 142.91
        },
        {
            "bank": "BRAC",
            "currency": "EUR",
            "buy": 139.3874,
            "sell": 142.0954
        },
        {
            "bank": "PRIME",
            "currency": "EUR",
            "buy": 139.1371,
            "sell": 142.1888
        }
    ]
}